corepytools.py
corepytools-0.0.14.dist-info/LICENSE.txt
corepytools-0.0.14.dist-info/METADATA
corepytools-0.0.14.dist-info/WHEEL
corepytools-0.0.14.dist-info/top_level.txt
corepytools-0.0.14.dist-info/RECORD
