Metadata-Version: 2.1
Name: corepytools
Version: 0.0.14
Summary: CorePy: XRF clustering tools to interpret and visualize geological core data
Home-page: https://github.com/Totilarson/CorePy
Author: Toti Larson
Author-email: totlarson@gmail.com
License: LICENSE.txt
Platform: UNKNOWN
Classifier: License :: OSI Approved :: MIT License
Classifier: Programming Language :: Python :: 3
Classifier: Programming Language :: Python :: 3.7
License-File: LICENSE.txt
